{
  "hash": "05a2abc2",
  "configHash": "1979e5c6",
  "lockfileHash": "d92ccf3b",
  "browserHash": "b286d26f",
  "optimized": {
    "vue": {
      "src": "../../../../node_modules/vue/dist/vue.runtime.esm-bundler.js",
      "file": "vue.js",
      "fileHash": "1046d9de",
      "needsInterop": false
    },
    "vitepress > @vue/devtools-api": {
      "src": "../../../../node_modules/@vue/devtools-api/lib/esm/index.js",
      "file": "vitepress___@vue_devtools-api.js",
      "fileHash": "6b51ac33",
      "needsInterop": false
    },
    "vitepress > @vueuse/core": {
      "src": "../../../../node_modules/@vueuse/core/index.mjs",
      "file": "vitepress___@vueuse_core.js",
      "fileHash": "bfce8b73",
      "needsInterop": false
    },
    "dy-virtual-table": {
      "src": "../../../../node_modules/dy-virtual-table/dist/dy-virtual-table.umd.js",
      "file": "dy-virtual-table.js",
      "fileHash": "4d0d1416",
      "needsInterop": true
    },
    "highlight.js": {
      "src": "../../../../node_modules/highlight.js/es/index.js",
      "file": "highlight__js.js",
      "fileHash": "e19e3250",
      "needsInterop": false
    }
  },
  "chunks": {
    "chunk-VQ6C7ZYK": {
      "file": "chunk-VQ6C7ZYK.js"
    },
    "chunk-CEQRFMJQ": {
      "file": "chunk-CEQRFMJQ.js"
    }
  }
}